shiny_api/applescript/rc_search_by_number.applescript
shiny_api/classes/__init__.py
shiny_api/classes/api_serial.py
shiny_api/classes/google_mysql.py
shiny_api/classes/google_sheets.py
shiny_api/classes/homeassistant.py
shiny_api/classes/ipsw_me_ipsw.py
shiny_api/classes/ls_customer.py
shiny_api/classes/ls_item.py
shiny_api/classes/ls_workorder.py
shiny_api/classes/phonecheck.py
shiny_api/classes/sickw_results.py
shiny_api/config/__init__.py
shiny_api/config/age.json
shiny_api/config/config.json
shiny_api/config/devices.json
shiny_api/config/secret.json.sample
shiny_api/main.py
shiny_api/modules/__init__.py
shiny_api/modules/att_unlock.py
shiny_api/modules/cogs/chatgpt_cog.py
shiny_api/modules/cogs/exception_handler.py
shiny_api/modules/cogs/homeassistant_cog.py
shiny_api/modules/cogs/label_cog.py
shiny_api/modules/cogs/ls_cog.py
shiny_api/modules/cogs/phonecheck_cog.py
shiny_api/modules/cogs/setup_cog.py
shiny_api/modules/cogs/sickw_cog.py
shiny_api/modules/cogs/trello_cog.py
shiny_api/modules/connect_ls.py
shiny_api/modules/discord_bot.py
shiny_api/modules/get_ipsws.py
shiny_api/modules/label_print.py
shiny_api/modules/load_config.py
shiny_api/modules/ring_central.py
shiny_api/modules/update_customer_phone.py
shiny_api/modules/update_item_price.py
shiny_api/modules/weblistener.py
shiny_api/serial_camera.py
shiny_api-0.2.83.dist-info/METADATA
shiny_api-0.2.83.dist-info/WHEEL
shiny_api-0.2.83.dist-info/entry_points.txt
shiny_api-0.2.83.dist-info/RECORD
