Metadata-Version: 2.1
Name: shiny-api
Version: 0.2.83
Summary: Interface with LS and Camera Scanner
Author: Chris Busillo
Author-email: info@shinycomputers.com
Requires-Python: >=3.11.0,<3.12.0
Classifier: Programming Language :: Python :: 3
Classifier: Programming Language :: Python :: 3.11
Requires-Dist: Flask (>=2.2.3,<3.0.0)
Requires-Dist: beautifulsoup4 (>=4.11.2,<5.0.0)
Requires-Dist: discord (>=2.1.0,<3.0.0)
Requires-Dist: homeassistant-api (>=4.1.0,<5.0.0)
Requires-Dist: kivy (>=2.2.0.dev0,<3.0.0)
Requires-Dist: luddite (>=1.0.2,<2.0.0)
Requires-Dist: numpi (>=0.3.1,<0.4.0)
Requires-Dist: openai (>=0.27.0,<0.28.0)
Requires-Dist: opencv-python (>=4.7.0.68,<5.0.0.0)
Requires-Dist: pandas (>=1.5.3,<2.0.0)
Requires-Dist: py-applescript (>=1.0.3,<2.0.0)
Requires-Dist: py-trello (>=0.19.0,<0.20.0)
Requires-Dist: pygsheets (>=2.0.6,<3.0.0)
Requires-Dist: pytesseract (>=0.3.10,<0.4.0)
Requires-Dist: selenium (>=4.8.2,<5.0.0)
Requires-Dist: simple-zpl2 (>=0.3.0,<0.4.0)
Requires-Dist: sqlalchemy (>=2.0.4,<3.0.0)
Requires-Dist: waitress (>=2.1.2,<3.0.0)
